LICENSE
README.md
setup.py
furry_tool/__init__.py
furry_tool.egg-info/PKG-INFO
furry_tool.egg-info/SOURCES.txt
furry_tool.egg-info/dependency_links.txt
furry_tool.egg-info/requires.txt
furry_tool.egg-info/top_level.txt
furry_tool/docx_ops/__init__.py
furry_tool/docx_ops/docx_template.py
furry_tool/docx_ops/pdf2docx.py
furry_tool/io/__init__.py
furry_tool/io/dir_ops.py
test/__init__.py
test/test_dir_ops.py
test/test_docx_ops.py
test/test_pdf2docx.py