Metadata-Version: 2.1
Name: furry-tool
Version: 0.0.6
Summary: 个人工具集
Home-page: https://github.com/xsxz01/furry_tool.git
Author: AaronDoge
Author-email: pangyuyu@email.cn
License: Apache License 2.0
Keywords: python,furry_tool,toolkit
Classifier: Programming Language :: Python :: 3
License-File: LICENSE
